ihaveto/__init__.py
ihaveto/main.py
ihaveto-1.0.0.dist-info/DESCRIPTION.rst
ihaveto-1.0.0.dist-info/METADATA
ihaveto-1.0.0.dist-info/RECORD
ihaveto-1.0.0.dist-info/WHEEL
ihaveto-1.0.0.dist-info/entry_points.txt
ihaveto-1.0.0.dist-info/metadata.json
ihaveto-1.0.0.dist-info/top_level.txt
