Metadata-Version: 2.0
Name: ihaveto
Version: 1.0.0
Summary: IHAVETO: A simple todo list for Developers
Home-page: https://github.com/kjellberg/todode
Author: Rasmus Kjellberg
Author-email: rk@youngmedia.se
License: MIT
Keywords: TODO-list for terminal developers
Platform: UNKNOWN
Classifier: Development Status :: 3 - Alpha
Classifier: Intended Audience :: Developers
Classifier: Topic :: Software Development :: Build Tools
Classifier: License :: OSI Approved :: MIT License
Classifier: Programming Language :: Python :: 3
Classifier: Programming Language :: Python :: 3.2
Classifier: Programming Language :: Python :: 3.3
Classifier: Programming Language :: Python :: 3.4
Requires-Dist: peewee
